{
  "id": "snowflake",
  "service": "Snowflake",
  "version": 1,
  "category": "Data & Analytics",
  "description": "Snowflake integration with 5 pre-built routines.",
  "auth": {
    "type": "bearer",
    "properties": [
      {
        "name": "access_token",
        "required": true,
        "description": "API access token or bearer token.",
        "encrypted": true
      },
      {
        "name": "account_url",
        "required": true,
        "description": "Snowflake account URL (e.g. https://myaccount.snowflakecomputing.com)."
      },
      {
        "name": "jwt_token",
        "required": true,
        "description": "Snowflake JWT token.",
        "encrypted": true
      }
    ]
  },
  "icon": "<svg viewBox=\"0 0 24 24\" width=\"20\" height=\"20\" fill=\"#29B5E8\"><path d=\"M12 0l2.5 4.3 2.5-1.4v2.9L20 7.2l-2.5 4.3L20 12l-2.5.5 2.5 4.3-3 1.4v2.9l-2.5-1.4L12 24l-2.5-4.3L7 21.1v-2.9l-3-1.4 2.5-4.3L4 12l2.5-.5L4 7.2l3-1.4V2.9l2.5 1.4L12 0z\"/></svg>",
  "docsUrl": "https://docs.snowflake.com/en/developer-guide/sql-api/reference",
  "defaultHeaders": {
    "Accept": "application/json",
    "Content-Type": "application/json"
  },
  "routines": [
    {
      "id": "pipe_create",
      "name": "Snowflake Pipe Create",
      "description": "POST /api/v2/statements",
      "method": "POST",
      "path": "/api/v2/statements",
      "inputs": [
        {
          "name": "Pipe Name",
          "required": true,
          "mapTo": "Pipe Name"
        },
        {
          "name": "Database",
          "required": true,
          "mapTo": "Database"
        },
        {
          "name": "Schema",
          "required": true,
          "mapTo": "Schema"
        },
        {
          "name": "Warehouse",
          "required": true,
          "mapTo": "Warehouse"
        },
        {
          "name": "Copy Statement",
          "required": true,
          "mapTo": "Copy Statement"
        },
        {
          "name": "Auto Ingest",
          "required": false,
          "mapTo": "Auto Ingest"
        }
      ],
      "outputs": [
        {
          "name": "Statement Handle",
          "path": "statement_handle"
        },
        {
          "name": "Status",
          "path": "status"
        },
        {
          "name": "Response Body",
          "path": "response_body"
        },
        {
          "name": "Response Code",
          "path": "response_code"
        },
        {
          "name": "Handler Error Message",
          "path": "handler_error_message"
        }
      ]
    },
    {
      "id": "query_execute",
      "name": "Snowflake Query Execute",
      "description": "POST /api/v2/statements",
      "method": "POST",
      "path": "/api/v2/statements",
      "inputs": [
        {
          "name": "Statement",
          "required": true,
          "mapTo": "Statement"
        },
        {
          "name": "Database",
          "required": true,
          "mapTo": "Database"
        },
        {
          "name": "Schema",
          "required": true,
          "mapTo": "Schema"
        },
        {
          "name": "Warehouse",
          "required": true,
          "mapTo": "Warehouse"
        },
        {
          "name": "Timeout",
          "required": false,
          "mapTo": "Timeout"
        }
      ],
      "outputs": [
        {
          "name": "Statement Handle",
          "path": "statement_handle"
        },
        {
          "name": "Status",
          "path": "status"
        },
        {
          "name": "Data JSON",
          "path": "data_json"
        },
        {
          "name": "Result Set Metadata",
          "path": "result_set_metadata"
        },
        {
          "name": "Response Body",
          "path": "response_body"
        },
        {
          "name": "Response Code",
          "path": "response_code"
        },
        {
          "name": "Handler Error Message",
          "path": "handler_error_message"
        }
      ]
    },
    {
      "id": "stage_upload",
      "name": "Snowflake Stage Upload",
      "description": "POST /api/v2/statements",
      "method": "POST",
      "path": "/api/v2/statements",
      "inputs": [
        {
          "name": "Stage Path",
          "required": true,
          "mapTo": "Stage Path"
        },
        {
          "name": "Database",
          "required": true,
          "mapTo": "Database"
        },
        {
          "name": "Schema",
          "required": true,
          "mapTo": "Schema"
        },
        {
          "name": "Warehouse",
          "required": true,
          "mapTo": "Warehouse"
        },
        {
          "name": "File Data",
          "required": true,
          "mapTo": "File Data"
        }
      ],
      "outputs": [
        {
          "name": "Statement Handle",
          "path": "statement_handle"
        },
        {
          "name": "Status",
          "path": "status"
        },
        {
          "name": "Response Body",
          "path": "response_body"
        },
        {
          "name": "Response Code",
          "path": "response_code"
        },
        {
          "name": "Handler Error Message",
          "path": "handler_error_message"
        }
      ]
    },
    {
      "id": "task_create",
      "name": "Snowflake Task Create",
      "description": "POST /api/v2/statements",
      "method": "POST",
      "path": "/api/v2/statements",
      "inputs": [
        {
          "name": "Task Name",
          "required": true,
          "mapTo": "Task Name"
        },
        {
          "name": "Database",
          "required": true,
          "mapTo": "Database"
        },
        {
          "name": "Schema",
          "required": true,
          "mapTo": "Schema"
        },
        {
          "name": "Warehouse",
          "required": true,
          "mapTo": "Warehouse"
        },
        {
          "name": "Schedule",
          "required": true,
          "mapTo": "Schedule"
        },
        {
          "name": "Sql Statement",
          "required": true,
          "mapTo": "Sql Statement"
        }
      ],
      "outputs": [
        {
          "name": "Statement Handle",
          "path": "statement_handle"
        },
        {
          "name": "Status",
          "path": "status"
        },
        {
          "name": "Response Body",
          "path": "response_body"
        },
        {
          "name": "Response Code",
          "path": "response_code"
        },
        {
          "name": "Handler Error Message",
          "path": "handler_error_message"
        }
      ]
    },
    {
      "id": "test",
      "name": "Snowflake Connection Test",
      "description": "GET /",
      "method": "GET",
      "path": "/",
      "inputs": [],
      "outputs": [
        {
          "name": "Response Code",
          "path": "response_code"
        },
        {
          "name": "Connected",
          "path": "connected"
        }
      ]
    }
  ],
  "baseUrl": "https://ACCOUNT.snowflakecomputing.com"
}
